openai_to_codex_wrapper/__init__.py
openai_to_codex_wrapper/cli.py
openai_to_codex_wrapper/server.py
openai_to_codex_wrapper/version.py
openai_to_codex_wrapper-0.1.3.dist-info/licenses/LICENSE
openai_to_codex_wrapper-0.1.3.dist-info/METADATA
openai_to_codex_wrapper-0.1.3.dist-info/WHEEL
openai_to_codex_wrapper-0.1.3.dist-info/entry_points.txt
openai_to_codex_wrapper-0.1.3.dist-info/top_level.txt
openai_to_codex_wrapper-0.1.3.dist-info/RECORD
