Metadata-Version: 2.4
Name: openai-to-codex-wrapper
Version: 0.1.3
Summary: CLI to manage the OpenAI to Codex Wrapper API server
Home-page: https://github.com/teabranch/openai-to-codex-wrapper
Author: Ori Nachum
Author-email: ori.nachum@gmail.com
Classifier: Programming Language :: Python :: 3
Classifier: License :: OSI Approved :: MIT License
Classifier: Operating System :: OS Independent
Classifier: Environment :: Web Environment
Requires-Python: >=3.7
License-File: LICENSE
Requires-Dist: fastapi
Requires-Dist: uvicorn
Requires-Dist: httpx
Requires-Dist: pydantic
Requires-Dist: python-dotenv
Dynamic: author
Dynamic: author-email
Dynamic: classifier
Dynamic: description
Dynamic: description-content-type
Dynamic: home-page
Dynamic: license-file
Dynamic: requires-dist
Dynamic: requires-python
Dynamic: summary
